{
  "strategy_name": "AdvancedGridTradingStrategy",
  "strategy_type": "simple",
  "symbol": "EURUSD",
  "timeframe": "H1",
  "performance_metrics": "PortfolioMetrics(total_return=np.float64(-626.0000000000229), net_profit=np.float64(-62600000.00000228), sharpe_ratio=0.0, max_drawdown=0.0, total_trades=13, win_rate=0.38461538461538464, profit_factor=np.float64(0.8835479256080145), avg_trade=np.float64(-4815384.615384791), avg_winner=np.float64(15440000.000000685), avg_loser=np.float64(-17475000.000000715), largest_winner=np.float64(50000000.0000022), largest_loser=np.float64(-125000000.00000504), winning_trades=5, losing_trades=8, volatility=0.0)",
  "total_signals": 13,
  "trades": 13,
  "strategy_errors": [],
  "data_bars": 17521,
  "equity_curve": [
    {
      "timestamp": "2024-12-28 23:00:00+00:00",
      "equity": -62500000.00000228,
      "price": 12.23469
    },
    {
      "timestamp": "2024-12-29 00:00:00+00:00",
      "equity": -62500000.00000228,
      "price": 12.19246
    },
    {
      "timestamp": "2024-12-29 01:00:00+00:00",
      "equity": -62500000.00000228,
      "price": 12.20701
    },
    {
      "timestamp": "2024-12-29 02:00:00+00:00",
      "equity": -62500000.00000228,
      "price": 12.22851
    },
    {
      "timestamp": "2024-12-29 03:00:00+00:00",
      "equity": -62500000.00000228,
      "price": 12.29313
    },
    {
      "timestamp": "2024-12-29 04:00:00+00:00",
      "equity": -62500000.00000228,
      "price": 12.10072
    },
    {
      "timestamp": "2024-12-29 05:00:00+00:00",
      "equity": -62500000.00000228,
      "price": 11.99776
    },
    {
      "timestamp": "2024-12-29 06:00:00+00:00",
      "equity": -62500000.00000228,
      "price": 11.77408
    },
    {
      "timestamp": "2024-12-29 07:00:00+00:00",
      "equity": -62500000.00000228,
      "price": 11.67361
    },
    {
      "timestamp": "2024-12-29 08:00:00+00:00",
      "equity": -62500000.00000228,
      "price": 11.68197
    },
    {
      "timestamp": "2024-12-29 09:00:00+00:00",
      "equity": -62500000.00000228,
      "price": 11.60546
    },
    {
      "timestamp": "2024-12-29 10:00:00+00:00",
      "equity": -62500000.00000228,
      "price": 11.5763
    },
    {
      "timestamp": "2024-12-29 11:00:00+00:00",
      "equity": -62500000.00000228,
      "price": 11.68825
    },
    {
      "timestamp": "2024-12-29 12:00:00+00:00",
      "equity": -62500000.00000228,
      "price": 11.76158
    },
    {
      "timestamp": "2024-12-29 13:00:00+00:00",
      "equity": -62500000.00000228,
      "price": 11.58196
    },
    {
      "timestamp": "2024-12-29 14:00:00+00:00",
      "equity": -62500000.00000228,
      "price": 11.73849
    },
    {
      "timestamp": "2024-12-29 15:00:00+00:00",
      "equity": -62500000.00000228,
      "price": 11.65769
    },
    {
      "timestamp": "2024-12-29 16:00:00+00:00",
      "equity": -62500000.00000228,
      "price": 11.60494
    },
    {
      "timestamp": "2024-12-29 17:00:00+00:00",
      "equity": -62500000.00000228,
      "price": 11.41967
    },
    {
      "timestamp": "2024-12-29 18:00:00+00:00",
      "equity": -62500000.00000228,
      "price": 11.48502
    },
    {
      "timestamp": "2024-12-29 19:00:00+00:00",
      "equity": -62500000.00000228,
      "price": 11.5669
    },
    {
      "timestamp": "2024-12-29 20:00:00+00:00",
      "equity": -62500000.00000228,
      "price": 11.54431
    },
    {
      "timestamp": "2024-12-29 21:00:00+00:00",
      "equity": -62500000.00000228,
      "price": 11.48188
    },
    {
      "timestamp": "2024-12-29 22:00:00+00:00",
      "equity": -62500000.00000228,
      "price": 11.35641
    },
    {
      "timestamp": "2024-12-29 23:00:00+00:00",
      "equity": -62500000.00000228,
      "price": 11.34311
    },
    {
      "timestamp": "2024-12-30 00:00:00+00:00",
      "equity": -62500000.00000228,
      "price": 11.20549
    },
    {
      "timestamp": "2024-12-30 01:00:00+00:00",
      "equity": -62500000.00000228,
      "price": 11.27729
    },
    {
      "timestamp": "2024-12-30 02:00:00+00:00",
      "equity": -62500000.00000228,
      "price": 11.16563
    },
    {
      "timestamp": "2024-12-30 03:00:00+00:00",
      "equity": -62500000.00000228,
      "price": 11.20004
    },
    {
      "timestamp": "2024-12-30 04:00:00+00:00",
      "equity": -62500000.00000228,
      "price": 11.11559
    },
    {
      "timestamp": "2024-12-30 05:00:00+00:00",
      "equity": -62500000.00000228,
      "price": 11.10637
    },
    {
      "timestamp": "2024-12-30 06:00:00+00:00",
      "equity": -62500000.00000228,
      "price": 11.00468
    },
    {
      "timestamp": "2024-12-30 07:00:00+00:00",
      "equity": -62500000.00000228,
      "price": 11.16927
    },
    {
      "timestamp": "2024-12-30 08:00:00+00:00",
      "equity": -62500000.00000228,
      "price": 11.13252
    },
    {
      "timestamp": "2024-12-30 09:00:00+00:00",
      "equity": -62500000.00000228,
      "price": 11.23544
    },
    {
      "timestamp": "2024-12-30 10:00:00+00:00",
      "equity": -62500000.00000228,
      "price": 11.2051
    },
    {
      "timestamp": "2024-12-30 11:00:00+00:00",
      "equity": -62500000.00000228,
      "price": 11.26771
    },
    {
      "timestamp": "2024-12-30 12:00:00+00:00",
      "equity": -62500000.00000228,
      "price": 11.48869
    },
    {
      "timestamp": "2024-12-30 13:00:00+00:00",
      "equity": -62500000.00000228,
      "price": 11.53178
    },
    {
      "timestamp": "2024-12-30 14:00:00+00:00",
      "equity": -62500000.00000228,
      "price": 11.57124
    },
    {
      "timestamp": "2024-12-30 15:00:00+00:00",
      "equity": -62500000.00000228,
      "price": 11.59162
    },
    {
      "timestamp": "2024-12-30 16:00:00+00:00",
      "equity": -62500000.00000228,
      "price": 11.51838
    },
    {
      "timestamp": "2024-12-30 17:00:00+00:00",
      "equity": -62500000.00000228,
      "price": 11.64179
    },
    {
      "timestamp": "2024-12-30 18:00:00+00:00",
      "equity": -62500000.00000228,
      "price": 11.71841
    },
    {
      "timestamp": "2024-12-30 19:00:00+00:00",
      "equity": -62500000.00000228,
      "price": 11.94783
    },
    {
      "timestamp": "2024-12-30 20:00:00+00:00",
      "equity": -62500000.00000228,
      "price": 11.76955
    },
    {
      "timestamp": "2024-12-30 21:00:00+00:00",
      "equity": -62500000.00000228,
      "price": 11.75977
    },
    {
      "timestamp": "2024-12-30 22:00:00+00:00",
      "equity": -62500000.00000228,
      "price": 11.65271
    },
    {
      "timestamp": "2024-12-30 23:00:00+00:00",
      "equity": -62500000.00000228,
      "price": 11.73492
    },
    {
      "timestamp": "2024-12-31 00:00:00+00:00",
      "equity": -62500000.00000228,
      "price": 11.69044
    }
  ],
  "runtime_seconds": 9.451457738876343
}